pcdswidgets/__init__.py
pcdswidgets/_version.py
pcdswidgets/eps_byteindicator.py
pcdswidgets/table.py
pcdswidgets/utils.py
pcdswidgets/version.py
pcdswidgets/icons/__init__.py
pcdswidgets/icons/base.py
pcdswidgets/icons/gauges.py
pcdswidgets/icons/others.py
pcdswidgets/icons/pumps.py
pcdswidgets/icons/valves.py
pcdswidgets/icons/demo/__init__.py
pcdswidgets/icons/demo/__main__.py
pcdswidgets/tests/__init__.py
pcdswidgets/tests/conftest.py
pcdswidgets/tests/test_icons.py
pcdswidgets/tests/vacuum/__init__.py
pcdswidgets/tests/vacuum/test_base.py
pcdswidgets/tests/vacuum/test_mixins.py
pcdswidgets/tests/vacuum/test_symbols.py
pcdswidgets/vacuum/__init__.py
pcdswidgets/vacuum/base.py
pcdswidgets/vacuum/gauges.py
pcdswidgets/vacuum/mixins.py
pcdswidgets/vacuum/others.py
pcdswidgets/vacuum/pumps.py
pcdswidgets/vacuum/valves.py
pcdswidgets/vacuum/demo/__init__.py
pcdswidgets/vacuum/demo/__main__.py
pcdswidgets-0.10.0.dist-info/licenses/AUTHORS.rst
pcdswidgets-0.10.0.dist-info/licenses/LICENSE.md
pcdswidgets-0.10.0.dist-info/METADATA
pcdswidgets-0.10.0.dist-info/WHEEL
pcdswidgets-0.10.0.dist-info/entry_points.txt
pcdswidgets-0.10.0.dist-info/top_level.txt
pcdswidgets-0.10.0.dist-info/RECORD
